LICENSE
README.md
setup.cfg
setup.py
sasecli.egg-info/PKG-INFO
sasecli.egg-info/SOURCES.txt
sasecli.egg-info/dependency_links.txt
sasecli.egg-info/entry_points.txt
sasecli.egg-info/requires.txt
sasecli.egg-info/top_level.txt
sasecli_lib/__init__.py