Metadata-Version: 2.1
Name: sasecli
Version: 0.0.1b1
Summary: `Command-line access to available Prisma SASE CLI resources. (Specifically, Prisma SD-WAN as of now.)`
Home-page: https://github.com/ebob9/sasecli
Author: Aaron Edwards
Author-email: sasecli@ebob9.com
License: MIT
Classifier: Development Status :: 4 - Beta
Classifier: Intended Audience :: End Users/Desktop
Classifier: License :: OSI Approved :: MIT License
Classifier: Programming Language :: Python :: 3.10
Requires-Python: >=3.10.1
License-File: LICENSE
Requires-Dist: cloudgenix>=6.1.1b1
Requires-Dist: fuzzywuzzy>=0.17.0
Requires-Dist: pyyaml>=3.13
